verificadores/__init__.py
verificadores/cnpj.py
verificadores/cpf.py
pyverificadordocs-0.2.0.dist-info/LICENSE
pyverificadordocs-0.2.0.dist-info/WHEEL
pyverificadordocs-0.2.0.dist-info/METADATA
pyverificadordocs-0.2.0.dist-info/RECORD
