Metadata-Version: 2.1
Name: pyverificadordocs
Version: 0.2.0
Summary: Programa para fazer a verificação de documentos nacionais.
Author: Diaszano
Author-email: lucasdiiassantos@gmail.com
Requires-Python: >=3.10,<4.0
Classifier: Programming Language :: Python :: 3
Classifier: Programming Language :: Python :: 3.10
